[{"title":"Taboo New Sister ",
"preview":"https://www.themoviedb.org/t/p/w220_and_h330_face/wfEuhpvmA4QjY4CP0rHr4sysaoo.jpg",
"previews":"https://www.themoviedb.org/t/p/w1000_and_h563_face/wvY2GOWObIlbnXgGV9ZlPRFi7Ti.jpg",
"video":"https://www.mediafire.com/file/e6wav9tfj7o56h4/The_day_of_swapping_%25282017%2529.mp4/file",
"download":"https://www.mediafire.com/file/e6wav9tfj7o56h4/The_day_of_swapping_%25282017%2529.mp4/file",
"description":"ဇာတ်ကားလေးမှာတော့အသက်ကြီးပေမယ့်မပျက်စီးသေးပါဆိုတဲ့အတိုင်းဂီလမ်းဆိုတဲ့အဘိုးကြီးကသားဖြစ်သူဟီချောနဲ့ချွေးမဖြစ်သူဆွန်းဂျူကိုကလေးအတင်းမွေးခိုင်းပြီးမြေးချီရဖို့တိုက်တွန်းနေတဲ့အတွက်ကြောင့်သားဖြစ်သူနဲ့ချွေးမဖြစ်သူကလူမြင်ကွင်းဧည့်ခန်းထဲမှာတောင်မရှောင်ပဲလိင်ဆက်ဆံကြပါတော့တယ်။ဒါကိုဖအေဖြစ်သူကတွေ့သွားတဲ့အခါမနေနိုင်မထိုင်နိုင်တွေဖြစ်ပြီးစိတ်တွေထလာပါတော့တယ်။ဒါကြောင့်လည်းအခန်းထဲမှာနေရင်းမှန်းထုတာတွေ၊အိမ်ကိုမုန့်လာပေးတဲ့ဟွာဂျင်းဆိုသူနဲ့ကြုံးဖြစ်တာတွေ၊သားဖြစ်သူကား အက်ဆီးဒဆောင်းဝူရဲ့အဖေသူဌေးဂျန်ဟာမိန်းမမရှိတော့တဲ့နောက်တစ်ပင်လဲသော်တစ်ပင်ထူဆိုသလိုနောက်ထပ်မိန်မထပ်ယူလိုက်ပါတယ်။ဆောင်ဝူကမိထွေးဖြစ်သူနဲ့စကားမပြောသလိုမိထွေးဘက်ကပါလာတဲ့ကောင်းမလေးကိုလည်းစကားမပြောပဲခပ်ချေချေနေပါတယ်။ကွယ်ရာမှာတော့ကောင်မလေးကိုချောင်းကြည့်ပြီးသွားရည်ယိုနေတက်ပါတယ်။ကောင်မလေးရာသီလာထားတဲ့ဟာကိုအိမ်သာထဲမှာတွေ့လို့ယူထားပြီးရာသီသွေးပေနေတာကိုရှုပြီးအမြဲလိုလိုဂွင်းထုတက်ပါတယ်။မိထွေးဖြစ်သူကကောင်မလေးကိုအိမ်မှာလာနေခိုင်းတာကအကြံနဲ့ပါ။သူဌေးဂျန်ရဲ့ပိုက်ဆံစည်းစိမ်တွေကိုအပိုင်ကြံဖို့အတွက်ပါ။ဘာတွေဆက်ဖြစ်မလဲဆိုတာကတော့ဇာတ်ကားမှာကြည့်လိုက်ကြပါလို့ပြောပါရစေ။"},
{"title":"Obscene House 2 Slave Wife",
"preview":"https://static.xemovie.com/images/Film/Movies/ObsceneHouseSlaveWife.jpg",
"previews":"https://i.ytimg.com/vi/ITdHL3ZkI00/maxresdefault.jpg",
"video":"https://www.mediafire.com/file/r826cyliq51amyj/Obscene_House2.mp4/file",
"download":"https://www.mediafire.com/file/r826cyliq51amyj/Obscene_House2.mp4/file",
"description":"ဒီဇာတ်ကားလေးမှာတော့မကြာခင်မှာလက်ထပ်ကြတော့မယ့်ဂျောင်ယယ်လင်းနဲ့ဆောင်းဂျူတို့ကလက်မထပ်ခင်ကတည်းကဂျောင်ယယ်လင်းလက်ရှိနေနေတဲ့အိမ်ယာမှာပျော်ပါးကြပါတယ်။ဒါကိုအိမ်ယာကတာဝန်ရှိလုံခြုံရေးချွဲဂူလိုကသိသွားတဲ့အခါချမှတ်ထားတဲ့စည်းကမ်းချက်တွေဖောက်ဖျက်လို့ဒဏ်ကြေးဆောင်ခိုင်းပါတော့တယ်။ဒါကိုမကျေနပ်လို့ယယ်လင်းရဲ့ကောင်လေးကလုံခြုံရေးကိုထိုးကြိတ်ဆုံးမလိုက်တဲ့အခါအခြေအနေတွေကပိုဆိုးလာပြီးနောက်ဆုံးယယ်လင်းကဝန်ခံကတိထိုးပြီးလုံခြုံရေးရဲ့အသုံးတော်ခံဖြစ်သွားတဲ့အခါဘာတွေဆက်ဖြစ်ကြမလဲ၊လုံခြုံရေးချွဲဂူလိုကလည်းသူ့အိမ်ယာကမိန်းကလေးတွေကိုသူ့မယားအမှတ်နဲ့အားရပါးရစော်တာတွေကိုတဝကြီးစောင့်ကြည့်ရမယ့်ဇာတ်ကားကောင်းလေးပဲဖြစ်ပါတော့တယ်။"},
{"title":"SistersVirus(2020)",
"preview":"https://www.hancinema.net/photos/photo1299453.jpg",
"previews":"https://www.hancinema.net/photos/photo1299455.jpg",
"video":"https://www.mediafire.com/file/8l9zij2bcg0dw4q/Sisters_Virus_%25282020%2529.mp4/file",
"download":"https://www.mediafire.com/file/8l9zij2bcg0dw4q/Sisters_Virus_%25282020%2529.mp4/file",
"description":"ဇာတ်လမ်းအကျဉ်းကတော့ယောင်းဝူဟာမိန်းမဖြစ်သူရဲ့ညီအစ်မနှစ်ယောက်အတူနေတဲ့သူပေါ့တစ်နေ့တော့မျိူးသစ်ဗိုင်းရပ်စ်တစ်ခု ပျံ့နှံချိန်မှာတော့စိတ်မကောင်းစွာနဲ့ယောင်းဝူရဲ့မိန်းမဖြစ်သူဂျီနာဟာပိုးကူးပြီးဆေးကုသဖို့သွားတဲ့အချိန်မှာယောင်းဝူဟာမိန်းမရဲ့အစ်မဖြစ်သူနဲ့ညီမဖြစ်သူနဲ့အတူ Home Q ဖို့နေခဲ့ရတယ်။တစ်နေ့ကျယောင်းဝူရဲ့ခယ်မဖြစ်သူကပိုးကူးစက်ပြီးဆေးရုံလည်းပို့လို့မရတဲ့အချိန်မှာတော့သူတို့ရဲ့ကြိုးစားလေ့လာမှုနဲ့အတူတကုသနည်းတစ်ခုကိုတွေ့ရှိခဲ့တယ် သရုပ်ဆောင်လေးတွေကလဲအသစ်လေးတွေဆိုတော့သဘောကျစရာမျက်စိကျစရာလေးတွေပါပဲ။"},
{"title":"Boarding House For Couples",
"preview":"https://imagetot.com/images/2021/08/27/c3a154df0ba9d726c31777e0ea213aeb.jpg",
"previews":"https://imagetot.com/images/2021/08/27/c3a154df0ba9d726c31777e0ea213aeb.jpg",
"video":"https://www.mediafire.com/file/8b756vg4x5fcdfb/Boarding_House_For_Couples.mp4/file",
"download":"https://www.mediafire.com/file/8b756vg4x5fcdfb/Boarding_House_For_Couples.mp4/file",
"description":"ဒီဇာတ်ကားလေးမှာတော့အဆောင်ငှါးစားပြီးစီးပွားရေးလုပ်နေတဲ့အဆောင်မှူးအွန်းနာတစ်ယောက်မမျှော်လင့်ဘဲယောက်ျားလေးတွေကိုအဆောင်ငှါးမိရာမှဇာတ်လမ်းကစပါတော့တယ်။ယခင်တည်းကအဆောင်မှာရောက်နှင့်ပြီးသားကျောင်းသူဂျီဆူရေချိုးနေချိန်မှာနောက်မှရောက်လာတဲ့ကျောင်းသားဂယောင်ဂျင်းကရေချိုးခန်းတံခါးကိုမဆင်မခြင်ဖွင့်မိရာကအစပြု၍ဇာတ်လမ်းတွေစဖြစ်ကာအဆောင်မှူးကိုယ်တိုင်သိရှိသွားတော့မိန်းကလေးချင်းသာအဆောင်ငှါးချင်စိတ်တွေဖြစ်ပေါ်လာပေမယ့်ကျောင်းသားဂျွန်နိုနဲ့အဆောင်မှူးတို့ဇာတ်လမ်းခင်းကြရင်းပြေလည်သွားကာနောက်ဆုံးမှာတော့စုံတွဲများကိုသာအဆောင်ငှါးရန်ဆုံးဖြတ်လိုက်ကြပါတော့တယ်။အဆောင်ထဲမှာပဲsexဇာတ်လမ်းတွေဖြစ်ကြတာမို့လို့မလွတ်တမ်းကြည့်ရှုသင့်တဲ့ဇာတ်ကားလေးပဲဖြစ်ပါတော့တယ်။"},
{"title":"Young sister in law 5",
"preview":"https://photos.hancinema.net/photos/photo1109657.jpg",
"previews":"https://www.hancinema.net/photos/photo1109828.jpg",
"video":"https://www.mediafire.com/file/0yk6fbzvzhjpuoc/Young_Sister_In_Law_5_%25282019%2529.mp4/file",
"download":"https://www.mediafire.com/file/0yk6fbzvzhjpuoc/Young_Sister_In_Law_5_%25282019%2529.mp4/file",
"description":"ဒီဇာတ်ကားလေးမှာတော့ဖောက်ပြန်တတ်တဲ့စရိုက်ရှိတဲ့အွန်းဂျီကသူ့ထက်အသက်အများကြီးကွာတဲ့ချမ်းသာတဲ့သူအူဆောင်းနဲ့လက်ထပ်ထားပါတယ်။အွန်းဂျီမှာညီမလေးဘုံးဆွန်းလည်းရှိနေပြီးသူကလည်းခဲအိုအူဆောင်းနဲ့ဇာတ်လမ်းမကင်းသူလေးပေါ့။တစ်နေ့တော့အလုပ်ဝင်ဖို့အတွက်စာလုပ်ရတာအနှောင့်အယှက်ဖြစ်နေတဲ့အူဆောင်းရဲ့သူငယ်ချင်းဖြစ်သူထယ်ဆူကိုအိမ်မှာလာနေဖို့ပြောလိုက်ရင်းကနေ ထယ်ဆူနဲ့သူ့မိန်းမနဲ့ဘယ်လိုဇာတ်လမ်းလေးတွေဖြစ်လာကြမလဲဘယ်လိုအဆုံးသတ်မလဲဆိုတာကိုစောင့်ကြည့်ရမယ့်ဇာတ်ကားကောင်းလေးပဲဖြစ်ပါတယ်။"},
{"title":"Female Hostel 2017",
"preview":"https://i.mydramalist.com/JpEoXc.jpg?v=1",
"previews":"https://photos.hancinema.net/photos/photo841430.jpg",
"video":"https://www.mediafire.com/file/eelggn79je4wibv/Female_Hostel_%25282017%2529.mp4/file",
"download":"https://www.mediafire.com/file/eelggn79je4wibv/Female_Hostel_%25282017%2529.mp4/file",
"description":"ကိုရီးယားကိုနိုင်ငံခြားကနေကျောင်းလာတက်တဲ့ကျောင်းသူတွေအတွက်သီးသန့်ဖွင့်ထားတဲ့အဆောင်ပိုင်ရှင်နဲ့လုပ်ဖေါ်ကိုင်ဖက်ကနှာထန်တဲ့ဘဲတွေဖြစ်ပါတယ်။သူတို့ဖွင့်ထားတဲ့အဆောင်မှာလာတည်းတဲ့ကျောင်းသူတွေကိုဘယ်လိုဘူးမလဲဘယ်လိုကြံပြီးဘယ်လိုဖောင်းဒိုင်းကြမလဲဆိုတာဇာတ်ကားမှာပဲကြည့်ရှု့ကြပါလို့ပြောချင်ပါတယ်။"},
 
 {"title":"Beat Up Husband (2021)",

"preview":"https://photos.hancinema.net/photos/photo1337959.jpg",

"previews":"https://photos.hancinema.net/photos/photo1337959.jpg",

"video":"https://www.mediafire.com/file/fm6dmlvcpawlwvt/Beat_Up_Husband_%25282021%2529_%25281%2529.mp4/file",

"download":"https://www.mediafire.com/file/fm6dmlvcpawlwvt/Beat_Up_Husband_%25282021%2529_%25281%2529.mp4/file",

"description":"ဒီဇာတ်ကားလေးမှာတော့မိန်းမဖြစ်သူဆိုယောင်းရဲ့မထင်ရင်မထင်သလိုအဆဲအဆိုခံရအရိုက်နှက်ခံရတဲ့ယောက်ျားဖြစ်သူဆန်းမင်းမှာအိမ်ထောင်ရေးဖောက်ပြန်မှုတွေဆက်တိုက်ဖြစ်လာပါတော့တယ်။ဒီလိုနဲ့သူငယ်ချင်းဖြစ်သူဂွန်းဘယ်ရဲ့မိန်းမဖြစ်သူမင်ယောင်းနဲ့ဖောက်ပြန်မိတဲ့အခါဂွန်းဘယ်ကသိသွားပါတော့တယ်။ဒါကြောင့်နစ်နာကြေးအနေနဲ့မိန်းမလဲစားဖို့တောင်းဆိုတဲ့အခါဘာတွေဆက်ဖြစ်ကြမလဲ၊အိမ်ထောင်ရေးအရှုပ်တော်ပုံထဲမှာနောက်ဆုံးအမှားကိုသိပြီးဝန်ခံကြတဲ့အခန်းလေးတွေလည်းပါတော့ငိုရမလိုရယ်ရမလိုဖြစ်စေတဲ့ဇာတ်လမ်းမျိုးကိုပေးစွမ်းနိုင်တဲ့ဇာတ်ကားကောင်းလေးပဲဖြစ်ပါတော့တယ်။"},

{"title":"Living With My Cousin 2017",

"preview":"http://photos.hancinema.net/photos/photo905556.jpg",

"previews":"https://i.ytimg.com/vi/GAz01N7scGk/maxresdefault.jpg",

"video":"https://www.mediafire.com/file/gum2n4baosv5zha/Living_With_My_Cousin_%25282017%2529.mp4/file",

"download":"https://www.mediafire.com/file/gum2n4baosv5zha/Living_With_My_Cousin_%25282017%2529.mp4/file",

"description":"ဇာတ်လမ်းကတော့ဝမ်းကွဲမောင်နှမတွေဖြစ်ကြတဲ့အင်ဂျင်နီယာကျောင်းသား Hyun-woo စာရေးဆရာမ Ji-yoon တို့အကြောင်းပဲဖြစ်ပါတယ်။ငယ်စဉ်တည်းကအတူတူနေထိုင်ကြီးပြင်းခဲ့ကြပေမယ့်ကွဲကွာခဲ့တာနှစ်နဲ့ချီကြာခဲ့ပြီးမှစာရေးဆရာမ Ji-yoonကအကြောင်းတစ်ခုကြောင့်Hyun-wooနေထိုင်တဲ့အိမ်မှာလာရောက်နေထိုင်ဖို့ဖြစ်လာတဲ့အခါ..ဖောင်းဒိုင်းအခန်းများစွာကိုရှု့စားရမှာပါ။ဘာတွေဆက်ဖြစ်ကြမလဲဆိုတာကိုဇာတ်ကားမှာကြည့်ကြပါလို့ပြောပါရစေ"},

{"title":"Taming The Younger Sister in law",

"preview":"http://photos.hancinema.net/photos/photo1321658.jpg",

"previews":"https://photos.hancinema.net/photos/photo1276617.jpg",

"video":"https://www.mediafire.com/file/livummvo70mqng2/Taming_The_Younger_Sister_in_law.mp4/file",

"download":"https://www.mediafire.com/file/livummvo70mqng2/Taming_The_Younger_Sister_in_law.mp4/file",

"description":"ဇာတ်လမ်းကတော့ ခယ်မလေးနဲ့ ခဲအိုတို့ကြားက ချစ်ခြင်းမေတ္တာဘွဲ့ ဇာတ်လမ်းလေးပဲဖြစ်ပါတယ်ဇာတ်လမ်းအကျဉ်းကို လိုရင်းပြောရရင် မိန်းမကိုလည်း ရှယ်ကြိတ် ခယ်မကိုလည်း ခိုးစားတဲ့ကားလေးပါ မိန်းမကလည်း အရင်က call girl ဆိုတော့အပြုအစုက ရှယ်ကောင်းသလို ဖွံ့ဖွံ့ထွားထွား အိုးကားကားပါ ဒါပေမယ့်အဆစ်ပါတဲ့ လိုက်ပွဲ ခယ်မလေးကလည်း သေးသေး ကျစ်ကျစ် တနိုင်တပိုင်လေးဆိုတော့နှစ်သီးစားဖို့ ကြံနေတဲ့ ခဲအိုတစ်ယောက် ရင်ထဲ အပူမီးတွေ ကြွတဲ့အကြောင်းကို သရုပ်ဖော်ရိုက်ကူးထားတာဖြစ်ပါတယ် ဆော်တွေကိုညွှန်းရရင် မိန်းမနေရာက

သရုပ်ဆောင်ထားတဲ့ ဆော်ကြီးက ပြည့်ပြည့် ဖောင်းဖောင်း တင်းပြည့်ကျပ်ပြည့်ဆိုဒ် ခယ်မလေးက လုးံလုံး ကျစ်ကျစ် ပိန်ပိန်ပါးပါး ဆိုဒ်လေးပါ

မိန်းမလုပ်သူက ရုပ်အရမ်းမချောပေမယ့် အကွက်ဆန်းတွေ တတ်ပါတယ် ခယ်မလေးကလည်း ရှယ်ထန်သလို ရုပ်လေးက ချစ်စရာလေးပါတစ်ချို့နေရာတွေ 18+ ဆိုပေမယ့် ကြည့်တတ်ရင် ကြည့်တတ်သလို မြင်နိုင်မယ့် ကားကောင်းလေးတစ်ကားလည်းဖြစ်ပါတယ်အကွက်ဆန်းတွေမှ လေ့လာချင်တယ် ဆရာတို့အတွက် အကွက်တွေ ချပြထားလို့ ဝင်လေ့လာသွားသင့်တဲ့ကားလေးပါ"},

{"title":"Younger Church Sister 2020",

"preview":"https://photos.hancinema.net/photos/photo1337947.jpg",

"previews":"https://photos.hancinema.net/photos/largephoto1338016.jpg",

"video":"https://www.mediafire.com/file/sqllv9domc7rtju/Younger_Church_Sister.mp4/file",

"download":"https://www.mediafire.com/file/sqllv9domc7rtju/Younger_Church_Sister.mp4/file",

"description":"ဒီဇာတ်ကားလေးမှာတော့ဘာသာတရားအရမ်းကိုင်းရှိုင်းတဲ့သူတွေဖြစ်ကြတဲ့ဂျူမီ့ကိုဆန်းထယ်ကအစ်ကိုဖြစ်သူအထန်ကောင်လေးနဲ့ချိတ်ပေးလိုက်တဲ့အခါဘာတွေဆက်ဖြစ်ကြမလဲ၊လက်မထပ်ရသေးဘဲsexလုပ်ရင်အပြစ်ရှိတယ်လို့ခံစားရတဲ့သူတို့နှစ်ဦးအတွက်sexဆိုတာကြီးကရုတ်တရက်ကြီးကြုံတွေ့လာရတဲ့အခါsexလုပ်နေရင်းဘယ်လိုအလွဲလေးတွေကြုံတွေ့ရမလဲဆိုတာကိုအစမှအဆုံးတိုင်လက်မလွှတ်တမ်းကြည့်ရမယ့်ဇာတ်ကားကောင်းလေးတစ်ကားပဲဖြစ်ပါတော့တယ်။"},

{"title":"Nasty Wife Husband Friend Taste 2021",

"preview":"https://encrypted-tbn0.gstatic.com/images?q=tbn:ANd9GcQILIhOzASVWdIPvvuZNFbLsZC4NHrNcVqQqQ&usqp=CAU",

"previews":"https://encrypted-tbn0.gstatic.com/images?q=tbn:ANd9GcTGLplZyw-cIXzw0NNfhbdawYFQ7tLFBT5ONw&usqp=CAU",

"video":"https://www.mediafire.com/file/82cp3rhinqcd9xl/Nasty_wife_husband_friend_taste_%25282021%2529.mp4/file",

"download":"https://www.mediafire.com/file/82cp3rhinqcd9xl/Nasty_wife_husband_friend_taste_%25282021%2529.mp4/file",

"description":"တစ်နေ့ဆူယောင်းရဲ့အမဖြစ်သူချွဲယောင်းကအမေနဲ့ရန်ဖြစ်ပြီးဆူယောင်းတို့လင်မယားနှစ်ယောက်နေတဲ့အိမ်မှာလာနေပါတယ်။အဲ့ညမှာပဲဆူယောင်းရဲ့ယောင်္ကျားဟာအမူးလွန်ပြီးအိမ်ပြန်လာခဲ့ပါတယ်။နောက်နေ့မနက်ချွဲယောင်းဟာရေချိုးပြီးအခန်းထဲကကုတင်ပေါ်မှာကုန်းပြီးပစ္စည်းတစ်ခုရှာနေပါတယ်။ရေစိုသဘက်အပိုင်းလေးပဲပတ်ဝတ်ထားတဲ့ချွဲယောင်းဟာကုန်းပြီးပစ္စည်းရှာနေတော့ဖင်အဟောင်းသားပေါ်နေပါတယ်။အဲ့အချိန်ဆူယောင်းရဲ့ငမူးသမားယောင်္ကျားနိုးလာပြီးအခန်းထဲဝင်လာတော့ဖင်ပြောင်ပြောင်နဲ့ကုန်းနေတဲ့ချွဲယောင်းကိုသူ့မိန်းမဆူယောင်းထင်ပြီးလီးထုတ်ပြီးပြောင်နေတဲ့ကုန်းနေတဲ့ဖင်ထဲကိုထိုးထည့်လိုက်ပါတော့တယ်။ဘာတွေဆက်ဖြစ်လာမလဲဆိုတာကိုဇာတ်ကားမှာကြည့်လိုက်ကြပါလို့ပြောပါရစေ"},

{"title":"Sensitive Mother And Daughter 2020",

"preview":"https://i.mydramalist.com/4jqJd_4c.jpg",

"previews":"https://photos.hancinema.net/photos/photo1212876.jpg",

"video":"https://www.mediafire.com/file/foaf8v43g882idv/Sensitive_Mother_and_Daughter_%25282020%2529.mp4/file",

"download":"https://www.mediafire.com/file/foaf8v43g882idv/Sensitive_Mother_and_Daughter_%25282020%2529.mp4/file",

"description":"ဒီဇာတ်ကားလေးမှာတော့အသက်အရွယ်ရလာပေမယ့်sexဆိုမရှောင်နိုင်သေးတဲ့အမေဖြစ်သူရဲ့မဆင်မခြင်လုပ်ရပ်တွေကြောင့်သမီးဖြစ်သူမင်ဟယ်မှာsexကိစ္စကိုစိတ်ဝင်စားမှန်းမသိတစ်စစနဲ့အာရုံစိုက်လာပါတော့တယ်။အဲဒီစိတ်ကြောင့်ပဲဆန့်ကျင်ဘက်လိင်နဲ့တွေ့တဲ့အခါမနေနိုင်မထိုင်နိုင်တွေဖြစ်ကာရုံးကလုပ်ဖော်ကိုင်ဖက်ဖြစ်သူနဲ့sexဖြစ်သွားကြတာတွေ၊အမေဖြစ်သူရဲ့ sex partner ကိုပါစားချင်စိတ်ဖြစ်ပေါ်လာတာတွေကြောင့်လိင်ပိုင်းဆိုင်ရာမှာစိတ်တွေတအားပြင်းထန်လာပြီးနောက်ဆုံးမှာဆရာဝန်နဲ့တိုင်ပင်ပြီးကုသဖို့ဖြစ်လာပါတော့တယ်။ဆရာဝန်ရဲ့ပြောကြားချက်အရအမေဖြစ်သူမှာသမီးအတွက်အချစ်စစ်ရှာပေးရင်းsexကိုအတူတူမျှဝေစားကြတာတွေ၊ဒါပေမယ့်နောက်ဆုံးမှာဘယ်လိုမှမသက်သာတဲ့အတွက်ကြောင့်ဆေးကုသပေးနေတဲ့ဆရာဝန်နဲ့ကျမှပဲသက်သာလာတာတွေစသဖြင့်ဇာတ်လမ်းအစမှသည်ဇာတ်လမ်းနောက်ဆုံးပိုင်း အထိsexကိုမှအသားပေးကြည့်ချင်နေတဲ့သူတွေအတွက်တဝကြီးကြည့်ရှုရမယ့်ဇာတ်လမ်းကောင်းလေးပဲဖြစ်ပါတော့တယ်"},

{"title":"ADULTERY Shh! Sisters Secret (2021)",

"preview":"https://photos.hancinema.net/photos/photo1340688.jpg",

"previews":"https://photos.hancinema.net/photos/photo1340685.jpg",

"video":"https://www.mediafire.com/file/0tjvx1zmf322oal/Shh%2521_Sisters_Secret.mp4/file",

"download":"https://www.mediafire.com/file/0tjvx1zmf322oal/Shh%2521_Sisters_Secret.mp4/file",

"description":"ဒီဇာတ်ကားလေးကတော့ကြည့်ဖူးသမျှဇာတ်လမ်းတွေထဲမှာဇာတ်အိမ်ခိုင်မာတယ်လို့ပြောလို့ရပါတယ်။တောကအဘွားအိမ်ကိုမရောက်ဖြစ်တာကြာနေပြီဖြစ်လို့လာလည်တဲ့ဆိုလ်းမြို့ကမြေးဖြစ်သူဟျောင်းဆူတစ်ယောက်ရောက်လာပါတော့တယ်။မမျှော်လင့်ဘဲအစ်မဖြစ်သူယောင်းဆုမှာယောက်ျားဖြစ်သူရဲ့လျစ်လျူရှုမှုတွေကြောင့်ယောက်ျားတကာနဲ့ဖောက်ပြန်နေတာကိုမောင်ဖြစ်သူတွေ့ရှ်ိသွားတဲ့အခါမှာဘယ်လိုတွေဆက်ဖြစ်ကြမလဲ။အစ်မရဲ့လျှို့ဝှက်ချက်တွေကိုရူးတိုးတိုးဆိုပြီးဘယ်လိုတွေဆက်ထိန်းထားမယ်ဆိုတာကိုတော့ အဆုံးထိကြည့်ပေးကြပါလို့သတင်းကောင်းပါးလိုက်ပါတယ်။"}]
